tayne
