Metadata-Version: 1.0
Name: tayne
Version: 0.1.2
Summary: companion to entr(1)
Home-page: https://github.com/eddieantonio/tayne
Author: Eddie Antonio Santos
Author-email: easantos@ualberta.ca
License: ISC
Platform: UNKNOWN
